pycrfsuite_spacing/__init__.py
pycrfsuite_spacing/tagger.py
pycrfsuite_spacing/transform.py
pycrfsuite_spacing-1.0.2.dist-info/DESCRIPTION.rst
pycrfsuite_spacing-1.0.2.dist-info/METADATA
pycrfsuite_spacing-1.0.2.dist-info/RECORD
pycrfsuite_spacing-1.0.2.dist-info/WHEEL
pycrfsuite_spacing-1.0.2.dist-info/metadata.json
pycrfsuite_spacing-1.0.2.dist-info/top_level.txt
