Metadata-Version: 2.0
Name: pycrfsuite-spacing
Version: 1.0.2
Summary: Pycrfsuite를 이용한 띄어쓰기 교정기
Requires-Dist: python-crfsuite (>=0.9.2)
